fastybird_virtual_connector/__init__.py
fastybird_virtual_connector/bootstrap.py
fastybird_virtual_connector/connector.py
fastybird_virtual_connector/entities.py
fastybird_virtual_connector/logger.py
fastybird_virtual_connector/types.py
tests/__init__.py
tests/pytests/__init__.py
fastybird_virtual_connector-0.11.0.dist-info/LICENSE.md
fastybird_virtual_connector-0.11.0.dist-info/METADATA
fastybird_virtual_connector-0.11.0.dist-info/WHEEL
fastybird_virtual_connector-0.11.0.dist-info/top_level.txt
fastybird_virtual_connector-0.11.0.dist-info/RECORD
