Metadata-Version: 2.1
Name: fastybird-virtual-connector
Version: 0.11.0
Summary: FastyBird IoT connector for virtual devices
Home-page: https://github.com/FastyBird/virtual-connector
Author: FastyBird
Author-email: code@fastybird.com
License: Apache Software License (Apache Software License 2.0)
Download-URL: https://github.com/FastyBird/virtual-connector/archive/0.11.0.tar.gz
Platform: UNKNOWN
Classifier: Development Status :: 4 - Beta
Classifier: Environment :: Console
Classifier: Environment :: Plugins
Classifier: Intended Audience :: Developers
Classifier: Intended Audience :: Education
Classifier: Intended Audience :: End Users/Desktop
Classifier: Intended Audience :: Information Technology
Classifier: Intended Audience :: Manufacturing
Classifier: Intended Audience :: System Administrators
Classifier: License :: OSI Approved :: Apache Software License
Classifier: Natural Language :: English
Classifier: Operating System :: OS Independent
Classifier: Programming Language :: PHP
Classifier: Programming Language :: Python
Classifier: Programming Language :: Python :: 3 :: Only
Classifier: Programming Language :: Python :: 3.7
Classifier: Programming Language :: Python :: 3.8
Classifier: Programming Language :: Python :: 3.9
Classifier: Programming Language :: Python :: 3.10
Classifier: Topic :: Communications
Classifier: Topic :: Home Automation
Classifier: Topic :: System :: Hardware
Requires-Python: >=3.7
License-File: LICENSE.md
Requires-Dist: fastnumbers
Requires-Dist: fastybird-devices-module
Requires-Dist: fastybird-metadata
Requires-Dist: kink
Requires-Dist: setuptools
Requires-Dist: whistle
